<?xml version="1.0" encoding="utf-8"?>
<Dependencies>
  <ProductDependencies>
    <Dependency Name="System.Device.Gpio" Version="0.1.0-prerelease.19314.3">
      <Uri>https://github.com/dotnet/iot</Uri>
      <Sha>f042be62cd1a54a4be24dfd4f506ad8a9009a236</Sha>
    </Dependency>
    <Dependency Name="Iot.Device.Bindings" Version="0.1.0-prerelease.19314.3">
      <Uri>https://github.com/dotnet/iot</Uri>
      <Sha>f042be62cd1a54a4be24dfd4f506ad8a9009a236</Sha>
    </Dependency>
  </ProductDependencies>
  <ToolsetDependencies>
    <Dependency Name="Microsoft.DotNet.Arcade.Sdk" Version="1.0.0-beta.19318.2">
      <Uri>https://github.com/dotnet/arcade</Uri>
      <Sha>dc538a29793fd56618d0fa3186e2388d47d00c19</Sha>
    </Dependency>
    <Dependency Name="Microsoft.DotNet.Helix.Sdk" Version="2.0.0-beta.19318.2">
      <Uri>https://github.com/dotnet/arcade</Uri>
      <Sha>dc538a29793fd56618d0fa3186e2388d47d00c19</Sha>
    </Dependency>
    <Dependency Name="Microsoft.DotNet.GenAPI" Version="1.0.0-beta.19318.2">
      <Uri>https://github.com/dotnet/arcade</Uri>
      <Sha>dc538a29793fd56618d0fa3186e2388d47d00c19</Sha>
    </Dependency>
  </ToolsetDependencies>
</Dependencies>
